flying_ioc/__init__.py
flying_ioc/base_container.py
flying_ioc/class_container.py
flying_ioc/factory_container.py
flying_ioc/ioc_decorator.py
flying_ioc/ioc_manager.py
flying_ioc/singleton_container.py
flying_ioc/value_container.py
flying_ioc-1.0.3.dist-info/LICENSE
flying_ioc-1.0.3.dist-info/METADATA
flying_ioc-1.0.3.dist-info/WHEEL
flying_ioc-1.0.3.dist-info/top_level.txt
flying_ioc-1.0.3.dist-info/RECORD
