Metadata-Version: 2.1
Name: flying-ioc
Version: 1.0.3
Summary: IoC for Humans
Home-page: https://github.com/ClanPlay/Python_IoC
Author: Asaf Semo, Dmitry Voronenkov
Author-email: asafsemo@gmail.com
License: UNKNOWN
Platform: UNKNOWN
Classifier: Programming Language :: Python :: 3
Classifier: License :: OSI Approved :: MIT License
Classifier: Operating System :: OS Independent
